security_check/__init__.py
security_check/execute.py
security_check-0.2.dist-info/METADATA
security_check-0.2.dist-info/WHEEL
security_check-0.2.dist-info/entry_points.txt
security_check-0.2.dist-info/top_level.txt
security_check-0.2.dist-info/RECORD
