Metadata-Version: 2.1
Name: security-check
Version: 0.2
Summary: Execute safety check with cvss scores
Home-page: UNKNOWN
Author: Claucio Rank
Author-email: clauciorank@gmail.com
License: UNKNOWN
Platform: UNKNOWN
Requires-Dist: beautifulsoup4
Requires-Dist: numba
Requires-Dist: requests
Requires-Dist: safety
